LICENSE
README.md
setup.cfg
setup.py
kenetsu/__init__.py
kenetsu/censor.py
kenetsu/cli.py
kenetsu/maileater.py
kenetsu/tail_loader.py
kenetsu.egg-info/PKG-INFO
kenetsu.egg-info/SOURCES.txt
kenetsu.egg-info/dependency_links.txt
kenetsu.egg-info/entry_points.txt
kenetsu.egg-info/requires.txt
kenetsu.egg-info/top_level.txt
tests/__init__.py
tests/conftest.py
tests/test_censor.py
tests/test_maillogeater.py
tests/test_tail_loader.py