Metadata-Version: 2.1
Name: kenetsu
Version: 0.2.0
Summary: Maillog summarizer
Home-page: https://github.com/elastic-infra/kenetsu
Author: Tomoya KABE
Author-email: kabe@elastic-infra.com
License: MIT
Platform: UNKNOWN
Classifier: Topic :: Communications :: Email
Classifier: Topic :: Internet :: Log Analysis
Classifier: Programming Language :: Python :: 2
Classifier: Programming Language :: Python :: 2.7
Classifier: Programming Language :: Python :: 3
Classifier: Programming Language :: Python :: 3.6
Classifier: Programming Language :: Python :: 3.8
Requires-Python: >=2.7
Provides-Extra: dev
